{
  "calendarRoot": "[data-testid='works-calendar']",
  "toolbar": "role=toolbar[name='Calendar navigation']",
  "viewButtons": {
    "month": "role=button[name='Month']",
    "week": "role=button[name='Week']",
    "day": "role=button[name='Day']",
    "agenda": "role=button[name='Agenda']",
    "schedule": "role=button[name='Schedule']"
  },
  "actions": {
    "addEvent": "role=button[name='Add new event']",
    "exportExcel": "role=button[name='Export to Excel']",
    "editEvent": "role=button[name='Edit event']",
    "closeDialog": "role=button[name='Close']"
  },
  "dialogs": {
    "editEvent": "role=dialog[name='Edit event']"
  },
  "monthView": {
    "dayCellByDateAttr": "[data-date='YYYY-MM-DD']"
  },
  "embed": {
    "hostIframe": "[data-testid='calendar-embed-iframe']"
  }
}
